{
  "type": "darg:corruption",
  "ingredients": [
    {
      "item": "darg:corrupted_essence_block"
    },
    {
      "item": "darg:corrupted_essence_block"
    },
    {"item": "minecraft:air"},
    {"item": "darg:corrupted_essence_block"},
    {"item": "darg:corrupted_essence_block"},{"item": "minecraft:corrupted_essence_block"},
    {"item": "minecraft:diamond"},{"item": "minecraft:"},{"item": "minecraft:air"},
    {
      "item": "darg:corrupted_essence_block"
    }
  ],
  "output": {
    "item": "darg:corrupted_cobblestone_bricks",
    "count": 4
  }
}